mseep_gensecai_mcp_poisoning_poc-1.0.0.dist-info/licenses/AUTHORS.md
mseep_gensecai_mcp_poisoning_poc-1.0.0.dist-info/licenses/LICENSE
src/__init__.py
src/attacks/__init__.py
src/attacks/base_attack.py
src/attacks/data_exfiltration.py
src/attacks/tool_hijacking.py
src/defenses/__init__.py
src/defenses/monitor.py
src/defenses/sanitizer.py
src/demo/__init__.py
src/demo/malicious_server.py
src/demo/secure_client.py
src/utils/__init__.py
src/utils/constants.py
src/utils/logger.py
tests/__init__.py
tests/test_attacks.py
tests/test_defenses.py
tests/test_integration.py
mseep_gensecai_mcp_poisoning_poc-1.0.0.dist-info/METADATA
mseep_gensecai_mcp_poisoning_poc-1.0.0.dist-info/WHEEL
mseep_gensecai_mcp_poisoning_poc-1.0.0.dist-info/top_level.txt
mseep_gensecai_mcp_poisoning_poc-1.0.0.dist-info/RECORD
